jumanpp_batch.py
jumanpp_batch-0.1.2.dist-info/METADATA
jumanpp_batch-0.1.2.dist-info/WHEEL
jumanpp_batch-0.1.2.dist-info/top_level.txt
jumanpp_batch-0.1.2.dist-info/RECORD
