Metadata-Version: 2.1
Name: jumanpp-batch
Version: 0.1.2
Summary: Apply juman++ to batch inputs in parallel
Home-page: https://github.com/kota7/jumanpp-batch
Author: Kota Mori
Author-email: kmori05@gmail.com
License: UNKNOWN
Platform: UNKNOWN
Classifier: Development Status :: 3 - Alpha
Classifier: Natural Language :: Japanese
Classifier: License :: OSI Approved :: MIT License
Classifier: Programming Language :: Python :: 2.7
Classifier: Programming Language :: Python :: 3.4
Classifier: Programming Language :: Python :: 3.5
Classifier: Programming Language :: Python :: 3.6
Classifier: Programming Language :: Python :: 3.7
Classifier: Programming Language :: Python :: 3.8
Requires-Dist: jaconv
Requires-Dist: ushlex
